README.rst
dronin-dumplog
dronin-getconfig
dronin-halt
dronin-logfsimport
dronin-shell
setup.cfg
setup.py
dronin/__init__.py
dronin/autotune.py
dronin/logfs.py
dronin/structshim.py
dronin/telemetry.py
dronin/uavo.py
dronin/uavo_collection.py
dronin/uavtalk.py
dronin.egg-info/PKG-INFO
dronin.egg-info/SOURCES.txt
dronin.egg-info/dependency_links.txt
dronin.egg-info/entry_points.txt
dronin.egg-info/requires.txt
dronin.egg-info/top_level.txt
dronin/logviewer/__init__.py
dronin/logviewer/logviewer.py
dronin/logviewer/plotdockarea.py